my_sorting_algorithms/__init__.py
my_sorting_algorithms/bubble_sort.py
my_sorting_algorithms/insertion_sort.py
my_sorting_algorithms/quick_sort.py
my_sorting_algorithms/selection_sort.py
my_sorting_algorithms_gioxon-0.1.dist-info/METADATA
my_sorting_algorithms_gioxon-0.1.dist-info/WHEEL
my_sorting_algorithms_gioxon-0.1.dist-info/top_level.txt
my_sorting_algorithms_gioxon-0.1.dist-info/RECORD
