Metadata-Version: 2.1
Name: my-sorting-algorithms-gioxon
Version: 0.1
Summary: Basic algorithms for sorting numbers
Home-page: https://gitlab.propulsion-home.ch/gioxon/week-3/tree/day4_/day4/my_sorting_algorithms
Author: Gio Xon
Author-email: giorgo.xonikis@gmail.com
License: MIT
Platform: UNKNOWN
